dksplit/__init__.py
dksplit/split.py
dksplit/models/__init__.py
dksplit/models/dksplit-int8.onnx
dksplit/models/dksplit.npz
dksplit-0.1.1.dist-info/licenses/LICENSE
dksplit-0.1.1.dist-info/METADATA
dksplit-0.1.1.dist-info/WHEEL
dksplit-0.1.1.dist-info/top_level.txt
dksplit-0.1.1.dist-info/RECORD
