Metadata-Version: 2.4
Name: dksplit
Version: 0.1.1
Summary: High-performance string segmentation using BiLSTM-CRF
Author-email: ABTdomain <info@abtdomain.com>
License: MIT
Project-URL: Homepage, https://abtdomain.com
Project-URL: Use_Case, https://domainkits.com
Project-URL: Repository, https://github.com/ABTdomain/dksplit
Keywords: nlp,segmentation,word-segmentation,domain,bilstm,crf,onnx
Classifier: Development Status :: 4 - Beta
Classifier: Intended Audience :: Developers
Classifier: License :: OSI Approved :: MIT License
Classifier: Programming Language :: Python :: 3
Classifier: Programming Language :: Python :: 3.8
Classifier: Programming Language :: Python :: 3.9
Classifier: Programming Language :: Python :: 3.10
Classifier: Programming Language :: Python :: 3.11
Classifier: Programming Language :: Python :: 3.12
Classifier: Programming Language :: Python :: 3.13
Classifier: Topic :: Text Processing :: Linguistic
Requires-Python: >=3.8
License-File: LICENSE
Requires-Dist: numpy>=1.19.0
Requires-Dist: onnxruntime>=1.10.0
Provides-Extra: gpu
Requires-Dist: onnxruntime-gpu>=1.10.0; extra == "gpu"
Provides-Extra: dev
Requires-Dist: pytest>=7.0; extra == "dev"
Dynamic: license-file
